[{"title":"Are there code examples of Unity IAP I can look at?","authorName":"Ben.","createdDate":"2016-07-15T14:23:02Z","updatedDate":"2017-04-27T03:50:05Z","labels":["IAP","In App Purchasing","Code","Examples"],"sections":[{"title":"Symptoms","content":["\n<li>I would like to see code examples of Unity IAP </li>\n"]},{"title":"Cause","content":["Example code and scenes&#xA0;can help make the whole In App Purchasing system much easier to understand."]},{"title":"Resolution","content":["Yes! An example scene/script comes with the Unity IAP plugin, titled <em>IAPDemo</em>. The relevant files can be found in the scenes and script folders of the Plugins/UnityPurchasing/ folder.&#xA0; You can also find a tutorial for setting up Unity IAP <a href=\"http://unity3d.com/learn/tutorials/topics/analytics/integrating-unity-iap-your-game\" target=\"_blank\">here</a>&#xA0;as well as additional samples in this repository:&#xA0;<a href=\"https://bitbucket.org/Unity-Technologies/unity-iap-samples\" target=\"_blank\" rel=\"nofollow noopener noreferrer\">https://bitbucket.org/Unity-Technologies/unity-iap-samples</a>"]},{"title":"More Information","content":[]}]}]