[{"title":"What is CS1502?","authorName":"Daniel Robledo.","createdDate":"2015-10-15T21:01:50Z","updatedDate":"2017-01-24T03:55:07Z","labels":["Scripting","CS1502","C#"],"sections":[{"title":"\nSymptoms\n\nYou are calling a method in your script and you receive the following error:\n\nerror CS1502: The best overloaded method match for `______________' has some invalid arguments.\nCause\nThis error occurs when the argument types being passed to a method do not match the parameter types of that method. If the called method is overloaded, then none of the overloaded versions has a signature that matches the argument types being passed.\n\nError presented in this example:\nerror CS1502: The best overloaded method match for `MyScript.MethodA(int, int)' has some invalid arguments.\nResolution\nCheck the types of the arguments that are being passed to the method and make sure that they match the arguments of the method being called.\n\nMore Information\nhttps://msdn.microsoft.com/en-us/library/b66k5sz9.aspx\n","content":[]}]}]