[{"title":"Why do I get a \"All compiler errors have to be fixed before you can enter playmode!\" error?","authorName":"Ben.","createdDate":"2015-09-03T16:17:50Z","updatedDate":"2017-06-11T06:03:13Z","labels":["Playmode","Compiler","Errors","All compiler errors have to be fixed"],"sections":[{"title":"Symptoms","content":["When trying to enter play mode, I am receiving&#xA0;the error below:","<span class=\"wysiwyg-color-black\">All compiler errors have to be fixed before entering playmode</span>"]},{"title":"Cause","content":["If any of the scripts in your Unity project have errors that do not allow Unity to compile the scripts, then this error will be displayed. You will not be able to enter play mode if this error is present."]},{"title":"Resolution","content":["You will need to look at all errors that are being flagged in the console and fix them.&#xA0;","Note: If you cannot see any errors in the console but the message still appears it may&#xA0;be an issue with a script using the namespace UnityEngine.Networking;","If the script is not being used then comment out the sections where the errors appear.&#xA0;","Once all scripts are free of errors, Unity can compile the scripts and you can enter play mode."]},{"title":"More Information","content":[]}]}]